polars_legacy_hash-0.0.5.dist-info/METADATA
polars_legacy_hash-0.0.5.dist-info/WHEEL
polars_legacy_hash-0.0.5.dist-info/licenses/LICENSE
polars_legacy_hash/__init__.py
polars_legacy_hash/_internal.pyi
polars_legacy_hash/py.typed
polars_legacy_hash/_internal.abi3.so
polars_legacy_hash-0.0.5.dist-info/RECORD
