Metadata-Version: 2.4
Name: polars_legacy_hash
Version: 0.0.5
Classifier: Programming Language :: Rust
Classifier: Programming Language :: Python :: Implementation :: CPython
Requires-Dist: packaging
License-File: LICENSE
Summary: Polars 0.20.10 hash function as a plugin library
Author: Matt Richards
Requires-Python: >=3.8
